switch.py
switch-1.0.2.dist-info/DESCRIPTION.rst
switch-1.0.2.dist-info/METADATA
switch-1.0.2.dist-info/pydist.json
switch-1.0.2.dist-info/RECORD
switch-1.0.2.dist-info/top_level.txt
switch-1.0.2.dist-info/WHEEL
